ws_streamer/data_announcer/__init__.py
ws_streamer/data_announcer/binance/__init__.py
ws_streamer/data_announcer/binance/distributing_ws_data.py
ws_streamer/data_announcer/deribit/__init__.py
ws_streamer/data_announcer/deribit/allocating_ohlc.py
ws_streamer/data_announcer/deribit/distributing_ws_data.py
ws_streamer/data_announcer/deribit/get_instrument_summary.py
ws_streamer/data_announcer/deribit/starter.py
ws_streamer/data_receiver/__init__.py
ws_streamer/data_receiver/binance.py
ws_streamer/data_receiver/deribit.py
ws_streamer/db_management/__init__.py
ws_streamer/db_management/redis_client.py
ws_streamer/db_management/sqlite_management.py
ws_streamer/messaging/__init__.py
ws_streamer/messaging/get_published_messages.py
ws_streamer/messaging/telegram_bot.py
ws_streamer/restful_api/__init__.py
ws_streamer/restful_api/binance/__init__.py
ws_streamer/restful_api/binance/api_url_end_point.toml
ws_streamer/restful_api/binance/binance.py
ws_streamer/restful_api/binance/download_binance.py
ws_streamer/restful_api/deribit/__init__.py
ws_streamer/restful_api/deribit/api_requests.py
ws_streamer/utilities/__init__.py
ws_streamer/utilities/caching.py
ws_streamer/utilities/pickling.py
ws_streamer/utilities/string_modification.py
ws_streamer/utilities/system_tools.py
ws_streamer/utilities/time_modification.py
ws_streamer-0.1.947.dist-info/METADATA
ws_streamer-0.1.947.dist-info/WHEEL
ws_streamer-0.1.947.dist-info/RECORD
