Metadata-Version: 2.4
Name: ws-streamer
Version: 0.1.947
Summary: app to relay data from exchanges
Author-email: "ven.ajie" <venoajie@gmail.com>
Requires-Python: >=3.12
Requires-Dist: aiohttp
Requires-Dist: aioredis>=2.0.1
Requires-Dist: aiosqlite==0.21.0
Requires-Dist: ccxt==4.4.74
Requires-Dist: dataclassy==1.0.1
Requires-Dist: loguru==0.7.3
Requires-Dist: oci==2.150.2
Requires-Dist: orjson==3.10.15
Requires-Dist: redis[hiredis]>=5.2.1
Requires-Dist: tomli==2.0.2
Requires-Dist: uvloop>=0.21.0
Requires-Dist: websockets==15.0
